pyavro/__init__.py
pyavro/util.py
pyavro/field/__init__.py
pyavro/field/field.py
pyavro/schema/__init__.py
pyavro/schema/schema.py
pyavro-0.4.0.dist-info/LICENSE
pyavro-0.4.0.dist-info/METADATA
pyavro-0.4.0.dist-info/WHEEL
pyavro-0.4.0.dist-info/top_level.txt
pyavro-0.4.0.dist-info/RECORD
